z3c.configurator-3.0-py3.9-nspkg.pth
z3c/configurator/README.txt
z3c/configurator/__init__.py
z3c/configurator/configurator.py
z3c/configurator/configure.zcml
z3c/configurator/i18n.py
z3c/configurator/interfaces.py
z3c/configurator/tests.py
z3c/configurator/vocabulary.py
z3c/configurator/browser/README.txt
z3c/configurator/browser/__init__.py
z3c/configurator/browser/configure.pt
z3c/configurator/browser/configure.zcml
z3c/configurator/browser/ftesting.zcml
z3c/configurator/browser/testing.py
z3c/configurator/browser/tests.py
z3c/configurator/browser/views.py
z3c.configurator-3.0.dist-info/LICENSE.txt
z3c.configurator-3.0.dist-info/METADATA
z3c.configurator-3.0.dist-info/WHEEL
z3c.configurator-3.0.dist-info/namespace_packages.txt
z3c.configurator-3.0.dist-info/top_level.txt
z3c.configurator-3.0.dist-info/RECORD
