Metadata-Version: 2.1
Name: z3c.configurator
Version: 3.0
Summary: Dynamic configuration
Home-page: https://github.com/zopefoundation/z3c.configurator
Author: Zope Community
Author-email: zope-dev@zope.dev
License: ZPL 2.1
Keywords: zope3 z3c configurator configuration
Classifier: Development Status :: 5 - Production/Stable
Classifier: Environment :: Web Environment
Classifier: Intended Audience :: Developers
Classifier: License :: OSI Approved :: Zope Public License
Classifier: Programming Language :: Python
Classifier: Programming Language :: Python :: 3
Classifier: Programming Language :: Python :: 3.7
Classifier: Programming Language :: Python :: 3.8
Classifier: Programming Language :: Python :: 3.9
Classifier: Programming Language :: Python :: 3.10
Classifier: Programming Language :: Python :: 3.11
Classifier: Natural Language :: English
Classifier: Operating System :: OS Independent
Classifier: Topic :: Internet :: WWW/HTTP
Classifier: Framework :: Zope :: 3
Requires-Python: >=3.7
License-File: LICENSE.txt
Requires-Dist: setuptools
Requires-Dist: zope.component
Requires-Dist: zope.i18nmessageid
Requires-Dist: zope.interface
Requires-Dist: zope.schema
Provides-Extra: ftest
Requires-Dist: zope.annotation ; extra == 'ftest'
Requires-Dist: zope.dublincore ; extra == 'ftest'
Requires-Dist: zope.formlib ; extra == 'ftest'
Requires-Dist: zope.securitypolicy ; extra == 'ftest'
Requires-Dist: zope.testbrowser ; extra == 'ftest'
Requires-Dist: zope.app.authentication ; extra == 'ftest'
Requires-Dist: zope.app.pagetemplate ; extra == 'ftest'
Requires-Dist: zope.app.testing ; extra == 'ftest'
Requires-Dist: zope.app.zcmlfiles ; extra == 'ftest'
Provides-Extra: test
Requires-Dist: zope.testing ; extra == 'test'
Requires-Dist: zope.testrunner ; extra == 'test'
Provides-Extra: zmi
Requires-Dist: zope.browserpage ; extra == 'zmi'
Requires-Dist: zope.formlib ; extra == 'zmi'
